cjk_textwrap/__init__.py
cjk_textwrap/cjk_textwrap.py
LICENSE
cjk_textwrap-0.1.0.dist-info/LICENSE
cjk_textwrap-0.1.0.dist-info/WHEEL
cjk_textwrap-0.1.0.dist-info/METADATA
cjk_textwrap-0.1.0.dist-info/RECORD
