Metadata-Version: 2.1
Name: cjk-textwrap
Version: 0.1.0
Summary: A flexible textwrapper for CJK string
Home-page: https://github.com/Hyiker/cjk-textwrap
License: MIT
Keywords: textwrap,CJK,Chinese
Author: Carbene
Author-email: hyikerhu0212@gmail.com
Requires-Python: >=3.7,<4.0
Classifier: License :: OSI Approved :: MIT License
Classifier: Programming Language :: Python :: 3
Classifier: Programming Language :: Python :: 3.10
Classifier: Programming Language :: Python :: 3.7
Classifier: Programming Language :: Python :: 3.8
Classifier: Programming Language :: Python :: 3.9
Requires-Dist: jieba (>=0.42.1,<0.43.0)
Project-URL: Repository, https://github.com/Hyiker/cjk-textwrap
